kptgraphs/__init__.py
kptgraphs/kptgraphs.py
kptgraphs-0.0.13.dist-info/LICENSE
kptgraphs-0.0.13.dist-info/METADATA
kptgraphs-0.0.13.dist-info/WHEEL
kptgraphs-0.0.13.dist-info/top_level.txt
kptgraphs-0.0.13.dist-info/RECORD
